anonymous_chatgpt/__init__.py
anonymous_chatgpt/__main__.py
anonymous_chatgpt/app.py
anonymous_chatgpt-0.0.4.dist-info/METADATA
anonymous_chatgpt-0.0.4.dist-info/WHEEL
anonymous_chatgpt-0.0.4.dist-info/entry_points.txt
anonymous_chatgpt-0.0.4.dist-info/top_level.txt
anonymous_chatgpt-0.0.4.dist-info/RECORD
