Metadata-Version: 2.1
Name: anonymous-chatgpt
Version: 0.0.4
Summary: A Python Client to interact with OpenAI's ChatGPT(GPT-3) model without authentication
Home-page: https://github.com/Mr-Destructive/anonymous-chatgpt
Author: Meet Gor
Author-email: gormeet711@gmail.com
Requires-Dist: requests
